{"url":"https:\/\/antares-floor.bitrix24.ru\/rest\/153\/t3tq7815dqe5c11i\/crm.lead.add.json","info":{"url":"https:\/\/antares-floor.bitrix24.ru\/rest\/153\/t3tq7815dqe5c11i\/crm.lead.add.json","content_type":"application\/json; charset=utf-8","http_code":200,"header_size":1032,"request_size":213,"filetime":-1,"ssl_verify_result":19,"redirect_count":0,"total_time":0.410594,"namelookup_time":0.002549,"connect_time":0.038532,"pretransfer_time":0.077222,"size_upload":354,"size_download":289,"speed_download":703,"speed_upload":862,"download_content_length":-1,"upload_content_length":354,"starttransfer_time":0.077237,"redirect_time":0,"redirect_url":"","primary_ip":"89.208.228.119","certinfo":[],"primary_port":443,"local_ip":"192.168.0.176","local_port":51170,"http_version":3,"protocol":2,"ssl_verifyresult":0,"scheme":"HTTPS","appconnect_time_us":76831,"connect_time_us":38532,"namelookup_time_us":2549,"pretransfer_time_us":77222,"redirect_time_us":0,"starttransfer_time_us":77237,"total_time_us":410594,"effective_method":"POST"},"params":{"method":"crm.lead.add","params":{"fields":{"TITLE":"\u0417\u0430\u044f\u0432\u043a\u0430 \u043e\u0442 \u041f\u0435\u0442\u0440 \u041f\u0435\u0442\u0440\u043e\u0432","COMMENTS":"\u0442\u0435\u0441\u0442","CONTACT_ID":23255,"SOURCE_ID":"WEBFORM","SOURCE_DESCRIPTION":"\u0417\u0430\u044f\u0432\u043a\u0430 \u0438\u0437 \u0441\u0430\u0439\u0442\u0430 Antares"}}},"result":{"result":57609,"time":{"start":1700471354.769552,"finish":1700471355.025557,"duration":0.25600504875183105,"processing":0.22742605209350586,"date_start":"2023-11-20T12:09:14+03:00","date_finish":"2023-11-20T12:09:15+03:00","operating_reset_at":1700471954,"operating":0.22740578651428223}}}